linkwiz-0.3.1.dist-info/METADATA
linkwiz-0.3.1.dist-info/WHEEL
linkwiz-0.3.1.dist-info/entry_points.txt
linkwiz-0.3.1.dist-info/licenses/LICENSE
linkwiz/__init__.py
linkwiz/__main__.py
linkwiz/browsers.py
linkwiz/config.py
linkwiz/core.py
linkwiz/gui.py
linkwiz/install.py
linkwiz/installation/linux_install.py
linkwiz/installation/win_install.py
linkwiz/launch.py
linkwiz/linux_browsers.py
linkwiz/match.py
linkwiz/types.py
linkwiz/win_browsers.py
linkwiz-0.3.1.dist-info/RECORD
