Metadata-Version: 2.1
Name: linkwiz
Version: 0.3.1
Summary: LinkWiz is a Linux tool that lets users select their preferred browser for opening links.
Author-Email: Rin <icealtria+github@gmail.com>
License: GPL-2.0-only
Classifier: Operating System :: POSIX :: Linux
Classifier: Operating System :: Microsoft :: Windows
Classifier: License :: OSI Approved :: GNU General Public License v2 (GPLv2)
Project-URL: Repository, https://github.com/icealtria/linkwiz
Requires-Python: <4.0,>=3.12
Requires-Dist: pyxdg<1.0,>=0.28
Requires-Dist: tomli-w<2.0.0,>=1.0.0
Requires-Dist: unalix-rev<1.0.0,>=0.9.1
